pyyaml_tags-1.0.4.dist-info/METADATA
pyyaml_tags-1.0.4.dist-info/RECORD
pyyaml_tags-1.0.4.dist-info/WHEEL
pyyaml_tags-1.0.4.dist-info/top_level.txt
yaml_tags/__about__.py
yaml_tags/__init__.py
yaml_tags/__version__.py
yaml_tags/base.py
yaml_tags/registry.py
yaml_tags/tags/__init__.py
yaml_tags/tags/env_tag.py
yaml_tags/tags/include_tag.py
yaml_tags/tags/random_tag.py
yaml_tags/tags/time_tag.py
